codeocean_mcp_server/__init__.py
codeocean_mcp_server/file_utils.py
codeocean_mcp_server/logging_config.py
codeocean_mcp_server/models.py
codeocean_mcp_server/search.py
codeocean_mcp_server/server.py
codeocean_mcp_server/tools/__init__.py
codeocean_mcp_server/tools/capsules.py
codeocean_mcp_server/tools/computations.py
codeocean_mcp_server/tools/custom_metadata.py
codeocean_mcp_server/tools/data_assets.py
codeocean_mcp_server-0.9.0.dist-info/METADATA
codeocean_mcp_server-0.9.0.dist-info/WHEEL
codeocean_mcp_server-0.9.0.dist-info/entry_points.txt
codeocean_mcp_server-0.9.0.dist-info/licenses/LICENSE
codeocean_mcp_server-0.9.0.dist-info/RECORD
