Metadata-Version: 2.4
Name: codeocean-mcp-server
Version: 0.9.0
Summary: Code Ocean MCP Server
Project-URL: Homepage, https://github.com/codeocean/codeocean-mcp-server
Project-URL: Issues, https://github.com/codeocean/codeocean-mcp-server/issues
Project-URL: Changelog, https://github.com/codeocean/codeocean-mcp-server/blob/main/CHANGELOG.md
Author-email: Code Ocean <dev@codeocean.com>
License-Expression: MIT
License-File: LICENSE
Classifier: License :: OSI Approved :: MIT License
Classifier: Operating System :: OS Independent
Classifier: Programming Language :: Python :: 3
Requires-Python: >=3.10
Requires-Dist: codeocean<0.15.0,>=0.14.0
Requires-Dist: mcp<1.13.0,>=1.12.0
